xtreme_vision/__init__.py
xtreme_vision/Detection/__init__.py
xtreme_vision/Detection/Custom/__init__.py
xtreme_vision/Detection/Custom/retinanet.py
xtreme_vision/Detection/Custom/tinyyolo.py
xtreme_vision/Detection/Custom/yolo.py
xtreme_vision/Detection/centernet/__init__.py
xtreme_vision/Detection/centernet/object_detection.py
xtreme_vision/Detection/centernet/pose_estimation.py
xtreme_vision/Detection/centernet/version.py
xtreme_vision/Detection/centernet/model/__init__.py
xtreme_vision/Detection/centernet/model/convolution.py
xtreme_vision/Detection/centernet/model/head.py
xtreme_vision/Detection/centernet/model/hourglass.py
xtreme_vision/Detection/centernet/model/object_detection.py
xtreme_vision/Detection/centernet/model/pose_estimation.py
xtreme_vision/Detection/centernet/model/residual.py
xtreme_vision/Detection/centernet/util/__init__.py
xtreme_vision/Detection/centernet/util/image.py
xtreme_vision/Detection/keras_resnet/__init__.py
xtreme_vision/Detection/keras_resnet/metrics.py
xtreme_vision/Detection/keras_resnet/backend/__init__.py
xtreme_vision/Detection/keras_resnet/backend/cntk_backend.py
xtreme_vision/Detection/keras_resnet/backend/common.py
xtreme_vision/Detection/keras_resnet/backend/tensorflow_backend.py
xtreme_vision/Detection/keras_resnet/backend/theano_backend.py
xtreme_vision/Detection/keras_resnet/benchmarks/__init__.py
xtreme_vision/Detection/keras_resnet/blocks/_1d.py
xtreme_vision/Detection/keras_resnet/blocks/_2d.py
xtreme_vision/Detection/keras_resnet/blocks/_3d.py
xtreme_vision/Detection/keras_resnet/blocks/__init__.py
xtreme_vision/Detection/keras_resnet/blocks/_time_distributed_2d.py
xtreme_vision/Detection/keras_resnet/classifiers/_2d.py
xtreme_vision/Detection/keras_resnet/classifiers/__init__.py
xtreme_vision/Detection/keras_resnet/layers/__init__.py
xtreme_vision/Detection/keras_resnet/layers/_batch_normalization.py
xtreme_vision/Detection/keras_resnet/models/_1d.py
xtreme_vision/Detection/keras_resnet/models/_2d.py
xtreme_vision-1.6.7.dist-info/LICENSE.txt
xtreme_vision-1.6.7.dist-info/METADATA
xtreme_vision-1.6.7.dist-info/WHEEL
xtreme_vision-1.6.7.dist-info/top_level.txt
xtreme_vision-1.6.7.dist-info/RECORD
