Metadata-Version: 2.1
Name: xtreme-vision
Version: 1.6.7
Summary: A Python Library for Computer Vision tasks like Object Detection, Segmentation, Pose Estimation etc
Home-page: https://github.com/Adeel-Intizar/Xtreme-Vision
Author: Adeel Intizar
Author-email: kingadeel2017@outlook.com
Maintainer: Adeel Intizar
Maintainer-email: kingadeel2017@outlook.com
License: MIT
Project-URL: Bug Reports, https://github.com/Adeel-Intizar/Xtreme-Vision/issues
Project-URL: Funding, https://patreon.com/adeelintizar
Project-URL: Say Thanks!, https://saythanks.io/to/kingadeel2017%40outlook.com
Project-URL: Source, https://github.com/Adeel-Intizar/Xtreme-Vision/
Keywords: object detection,computer vision,pose estimation,machine learning,deep learning,artificial intelligence,xtreme vision,segmentation,yolo,retinanet,centernet,yolov4,deeplab,tinyyolo
Platform: UNKNOWN
Classifier: Development Status :: 5 - Production/Stable
Classifier: Intended Audience :: Developers
Classifier: Intended Audience :: Education
Classifier: Intended Audience :: Information Technology
Classifier: License :: OSI Approved :: MIT License
Classifier: Natural Language :: English
Classifier: Operating System :: OS Independent
Classifier: Programming Language :: Python :: 3 :: Only
Classifier: Programming Language :: Python :: 3.5
Classifier: Programming Language :: Python :: 3.6
Classifier: Programming Language :: Python :: 3.7
Classifier: Programming Language :: Python :: 3.8
Classifier: Topic :: Scientific/Engineering :: Artificial Intelligence
Classifier: Topic :: Scientific/Engineering :: Image Processing
Classifier: Topic :: Scientific/Engineering :: Image Recognition
Requires-Python: >=3.5, <4
License-File: LICENSE.txt
